codegpt/__init__.py
codegpt/__main__.py
codegpt/files.py
codegpt/gpt_interface.py
codegpt/main.py
codegpt/parse.py
codegpt/prompts.py
codegpt/readme.md
codegpt-0.3.1.dist-info/entry_points.txt
codegpt-0.3.1.dist-info/LICENSE.txt
codegpt-0.3.1.dist-info/WHEEL
codegpt-0.3.1.dist-info/METADATA
codegpt-0.3.1.dist-info/RECORD
