Metadata-Version: 2.1
Name: codegpt
Version: 0.3.1
Summary: A CLI tool for developers using GPT-3.
Home-page: https://github.com/morganpartee/codegpt
License: GPL-3.0-or-later
Author: John Partee
Requires-Python: >=3.8,<4.0
Classifier: License :: OSI Approved :: GNU General Public License v3 or later (GPLv3+)
Classifier: Programming Language :: Python :: 3
Classifier: Programming Language :: Python :: 3.10
Classifier: Programming Language :: Python :: 3.8
Classifier: Programming Language :: Python :: 3.9
Requires-Dist: openai (>=0.2,<0.3)
Requires-Dist: python-magic (>=0.4.27,<0.5.0)
Requires-Dist: rich (>=12.6.0,<13.0.0)
Requires-Dist: typer (>=0.4.0,<0.5.0)
Project-URL: Repository, https://github.com/morganpartee/codegpt
